{
  "updatedAt": "2026-04-06T01:25:02.162Z",
  "filters": {
    "bouwjaarMin": 0,
    "oppervlakteMin": 0,
    "gebruiksdoelen": [
      "kantoorfunctie",
      "winkelfunctie",
      "bijeenkomstfunctie",
      "onderwijsfunctie",
      "industriefunctie"
    ],
    "vboStatuses": [
      "Verblijfsobject gevormd",
      "Verblijfsobject in gebruik",
      "Verblijfsobject in gebruik (niet ingemeten)",
      "Verblijfsobject buiten gebruik",
      "Verbouwing verblijfsobject",
      "Verblijfsobject ingetrokken",
      "Niet gerealiseerd verblijfsobject"
    ],
    "pandStatuses": [
      "Bouwvergunning verleend",
      "Bouw gestart",
      "Pand in gebruik",
      "Pand in gebruik (niet ingemeten)",
      "Sloopvergunning verleend",
      "Pand gesloopt",
      "Pand buiten gebruik",
      "Verbouwing pand"
    ]
  },
  "counts": {
    "1509": {
      "eligibleCount": 3944,
      "totalFetched": 44677,
      "pages": 47
    },
    "1586": {
      "eligibleCount": 1977,
      "totalFetched": 18774,
      "pages": 20
    },
    "1598": {
      "eligibleCount": 2034,
      "totalFetched": 26213,
      "pages": 29
    },
    "1641": {
      "eligibleCount": 2414,
      "totalFetched": 29018,
      "pages": 30
    },
    "1652": {
      "eligibleCount": 2464,
      "totalFetched": 33694,
      "pages": 36
    },
    "1655": {
      "eligibleCount": 3273,
      "totalFetched": 25583,
      "pages": 29
    },
    "1658": {
      "eligibleCount": 2309,
      "totalFetched": 39997,
      "pages": 42
    },
    "1659": {
      "eligibleCount": 1608,
      "totalFetched": 20568,
      "pages": 23
    },
    "1667": {
      "eligibleCount": 919,
      "totalFetched": 7979,
      "pages": 9
    },
    "1669": {
      "eligibleCount": 2559,
      "totalFetched": 40229,
      "pages": 44
    },
    "1681": {
      "eligibleCount": 3456,
      "totalFetched": 43843,
      "pages": 53
    },
    "1695": {
      "eligibleCount": 943,
      "totalFetched": 13761,
      "pages": 17
    },
    "1696": {
      "eligibleCount": 2136,
      "totalFetched": 28087,
      "pages": 29
    },
    "1700": {
      "eligibleCount": 2862,
      "totalFetched": 28728,
      "pages": 34
    },
    "1701": {
      "eligibleCount": 3507,
      "totalFetched": 35772,
      "pages": 46
    },
    "1706": {
      "eligibleCount": 1557,
      "totalFetched": 14877,
      "pages": 16
    },
    "1709": {
      "eligibleCount": 2549,
      "totalFetched": 29860,
      "pages": 32
    },
    "1711": {
      "eligibleCount": 2281,
      "totalFetched": 29461,
      "pages": 32
    },
    "1714": {
      "eligibleCount": 2571,
      "totalFetched": 25487,
      "pages": 26
    },
    "1719": {
      "eligibleCount": 2695,
      "totalFetched": 32701,
      "pages": 37
    },
    "1721": {
      "eligibleCount": 1964,
      "totalFetched": 30141,
      "pages": 31
    },
    "1723": {
      "eligibleCount": 1549,
      "totalFetched": 15135,
      "pages": 17
    },
    "1724": {
      "eligibleCount": 2076,
      "totalFetched": 28688,
      "pages": 29
    },
    "1728": {
      "eligibleCount": 1796,
      "totalFetched": 18175,
      "pages": 19
    },
    "1729": {
      "eligibleCount": 1130,
      "totalFetched": 16088,
      "pages": 18
    },
    "1740": {
      "eligibleCount": 2734,
      "totalFetched": 23857,
      "pages": 26
    },
    "1742": {
      "eligibleCount": 2179,
      "totalFetched": 22247,
      "pages": 25
    },
    "1771": {
      "eligibleCount": 1665,
      "totalFetched": 32798,
      "pages": 34
    },
    "1773": {
      "eligibleCount": 1541,
      "totalFetched": 18658,
      "pages": 20
    },
    "1884": {
      "eligibleCount": 3006,
      "totalFetched": 34251,
      "pages": 37
    },
    "1891": {
      "eligibleCount": 2124,
      "totalFetched": 21668,
      "pages": 24
    },
    "1894": {
      "eligibleCount": 3649,
      "totalFetched": 42206,
      "pages": 47
    },
    "1895": {
      "eligibleCount": 3206,
      "totalFetched": 39605,
      "pages": 53
    },
    "1896": {
      "eligibleCount": 1592,
      "totalFetched": 12855,
      "pages": 14
    },
    "1945": {
      "eligibleCount": 1806,
      "totalFetched": 35087,
      "pages": 39
    },
    "1949": {
      "eligibleCount": 4358,
      "totalFetched": 33845,
      "pages": 36
    },
    "1950": {
      "eligibleCount": 2704,
      "totalFetched": 36077,
      "pages": 41
    },
    "1961": {
      "eligibleCount": 3889,
      "totalFetched": 47291,
      "pages": 49
    },
    "1991": {
      "eligibleCount": 4291,
      "totalFetched": 49366,
      "pages": 52
    },
    "0047": {
      "eligibleCount": 1418,
      "totalFetched": 19820,
      "pages": 23
    },
    "0037": {
      "eligibleCount": 2207,
      "totalFetched": 26320,
      "pages": 32
    },
    "0059": {
      "eligibleCount": 2219,
      "totalFetched": 23062,
      "pages": 25
    },
    "0060": {
      "eligibleCount": 1862,
      "totalFetched": 15460,
      "pages": 17
    },
    "0072": {
      "eligibleCount": 2335,
      "totalFetched": 17702,
      "pages": 18
    },
    "0088": {
      "eligibleCount": 140,
      "totalFetched": 1637,
      "pages": 3
    },
    "0085": {
      "eligibleCount": 2143,
      "totalFetched": 23600,
      "pages": 26
    },
    "0093": {
      "eligibleCount": 1002,
      "totalFetched": 8885,
      "pages": 9
    },
    "0096": {
      "eligibleCount": 456,
      "totalFetched": 4565,
      "pages": 6
    },
    "0090": {
      "eligibleCount": 3124,
      "totalFetched": 37171,
      "pages": 39
    },
    "0098": {
      "eligibleCount": 3250,
      "totalFetched": 31739,
      "pages": 37
    },
    "0109": {
      "eligibleCount": 3093,
      "totalFetched": 35178,
      "pages": 42
    },
    "0106": {
      "eligibleCount": 2697,
      "totalFetched": 42090,
      "pages": 44
    },
    "0119": {
      "eligibleCount": 2460,
      "totalFetched": 26080,
      "pages": 28
    },
    "0147": {
      "eligibleCount": 1668,
      "totalFetched": 16164,
      "pages": 20
    },
    "0118": {
      "eligibleCount": 3629,
      "totalFetched": 37507,
      "pages": 40
    },
    "0148": {
      "eligibleCount": 2465,
      "totalFetched": 22612,
      "pages": 25
    },
    "0141": {
      "eligibleCount": 3967,
      "totalFetched": 48393,
      "pages": 51
    },
    "0158": {
      "eligibleCount": 2831,
      "totalFetched": 39763,
      "pages": 45
    },
    "0163": {
      "eligibleCount": 4322,
      "totalFetched": 39611,
      "pages": 45
    },
    "0166": {
      "eligibleCount": 3352,
      "totalFetched": 34542,
      "pages": 37
    },
    "0173": {
      "eligibleCount": 1666,
      "totalFetched": 18063,
      "pages": 19
    },
    "0168": {
      "eligibleCount": 2831,
      "totalFetched": 28579,
      "pages": 41
    },
    "0184": {
      "eligibleCount": 1406,
      "totalFetched": 10218,
      "pages": 12
    },
    "0177": {
      "eligibleCount": 2778,
      "totalFetched": 27796,
      "pages": 31
    },
    "0180": {
      "eligibleCount": 2490,
      "totalFetched": 25835,
      "pages": 31
    },
    "0197": {
      "eligibleCount": 1813,
      "totalFetched": 17736,
      "pages": 21
    },
    "0175": {
      "eligibleCount": 3393,
      "totalFetched": 33344,
      "pages": 42
    },
    "0171": {
      "eligibleCount": 6238,
      "totalFetched": 47926,
      "pages": 50
    },
    "0183": {
      "eligibleCount": 3058,
      "totalFetched": 40417,
      "pages": 53
    },
    "0209": {
      "eligibleCount": 2258,
      "totalFetched": 26862,
      "pages": 30
    },
    "0216": {
      "eligibleCount": 1210,
      "totalFetched": 16754,
      "pages": 17
    },
    "0221": {
      "eligibleCount": 545,
      "totalFetched": 7983,
      "pages": 10
    },
    "0213": {
      "eligibleCount": 3229,
      "totalFetched": 41113,
      "pages": 45
    },
    "0225": {
      "eligibleCount": 1547,
      "totalFetched": 13629,
      "pages": 15
    },
    "0226": {
      "eligibleCount": 1669,
      "totalFetched": 30011,
      "pages": 33
    },
    "0230": {
      "eligibleCount": 2320,
      "totalFetched": 28002,
      "pages": 29
    },
    "0232": {
      "eligibleCount": 2213,
      "totalFetched": 26967,
      "pages": 29
    },
    "0222": {
      "eligibleCount": 3530,
      "totalFetched": 40228,
      "pages": 44
    },
    "0246": {
      "eligibleCount": 1024,
      "totalFetched": 16510,
      "pages": 19
    },
    "0233": {
      "eligibleCount": 2050,
      "totalFetched": 39093,
      "pages": 41
    },
    "0243": {
      "eligibleCount": 2409,
      "totalFetched": 35196,
      "pages": 36
    },
    "0244": {
      "eligibleCount": 2144,
      "totalFetched": 28022,
      "pages": 32
    },
    "0263": {
      "eligibleCount": 3359,
      "totalFetched": 36734,
      "pages": 38
    },
    "0269": {
      "eligibleCount": 1871,
      "totalFetched": 24062,
      "pages": 27
    },
    "0252": {
      "eligibleCount": 1834,
      "totalFetched": 41060,
      "pages": 44
    },
    "0277": {
      "eligibleCount": 183,
      "totalFetched": 7423,
      "pages": 9
    },
    "0273": {
      "eligibleCount": 2070,
      "totalFetched": 30974,
      "pages": 33
    },
    "0279": {
      "eligibleCount": 600,
      "totalFetched": 7176,
      "pages": 8
    },
    "0274": {
      "eligibleCount": 1068,
      "totalFetched": 29172,
      "pages": 31
    },
    "0281": {
      "eligibleCount": 2480,
      "totalFetched": 27722,
      "pages": 28
    },
    "0293": {
      "eligibleCount": 1248,
      "totalFetched": 15651,
      "pages": 17
    },
    "0289": {
      "eligibleCount": 1700,
      "totalFetched": 28426,
      "pages": 30
    },
    "0294": {
      "eligibleCount": 1451,
      "totalFetched": 17861,
      "pages": 20
    },
    "0275": {
      "eligibleCount": 2547,
      "totalFetched": 42739,
      "pages": 46
    },
    "0302": {
      "eligibleCount": 1328,
      "totalFetched": 18310,
      "pages": 20
    },
    "0297": {
      "eligibleCount": 3786,
      "totalFetched": 37220,
      "pages": 39
    },
    "0301": {
      "eligibleCount": 3058,
      "totalFetched": 39422,
      "pages": 41
    },
    "0313": {
      "eligibleCount": 1312,
      "totalFetched": 14029,
      "pages": 15
    },
    "0308": {
      "eligibleCount": 2545,
      "totalFetched": 34121,
      "pages": 35
    },
    "0317": {
      "eligibleCount": 1992,
      "totalFetched": 24350,
      "pages": 26
    },
    "0339": {
      "eligibleCount": 1236,
      "totalFetched": 6975,
      "pages": 8
    },
    "0335": {
      "eligibleCount": 1744,
      "totalFetched": 18611,
      "pages": 21
    },
    "0312": {
      "eligibleCount": 2354,
      "totalFetched": 45863,
      "pages": 48
    },
    "0321": {
      "eligibleCount": 2467,
      "totalFetched": 38631,
      "pages": 40
    },
    "0331": {
      "eligibleCount": 2943,
      "totalFetched": 37095,
      "pages": 40
    },
    "0340": {
      "eligibleCount": 1821,
      "totalFetched": 24436,
      "pages": 26
    },
    "0351": {
      "eligibleCount": 1582,
      "totalFetched": 21850,
      "pages": 23
    },
    "0352": {
      "eligibleCount": 1163,
      "totalFetched": 18198,
      "pages": 20
    },
    "0342": {
      "eligibleCount": 3557,
      "totalFetched": 34976,
      "pages": 36
    },
    "0345": {
      "eligibleCount": 2736,
      "totalFetched": 36784,
      "pages": 37
    },
    "0353": {
      "eligibleCount": 1486,
      "totalFetched": 33335,
      "pages": 35
    },
    "0356": {
      "eligibleCount": 3337,
      "totalFetched": 44354,
      "pages": 46
    },
    "0376": {
      "eligibleCount": 2318,
      "totalFetched": 34395,
      "pages": 36
    },
    "0383": {
      "eligibleCount": 2088,
      "totalFetched": 30290,
      "pages": 33
    },
    "0388": {
      "eligibleCount": 1954,
      "totalFetched": 23746,
      "pages": 24
    },
    "0397": {
      "eligibleCount": 1672,
      "totalFetched": 22912,
      "pages": 25
    },
    "0399": {
      "eligibleCount": 1695,
      "totalFetched": 25996,
      "pages": 29
    },
    "0396": {
      "eligibleCount": 1961,
      "totalFetched": 48380,
      "pages": 51
    },
    "0400": {
      "eligibleCount": 3289,
      "totalFetched": 39494,
      "pages": 41
    },
    "0415": {
      "eligibleCount": 708,
      "totalFetched": 18234,
      "pages": 20
    },
    "0417": {
      "eligibleCount": 1358,
      "totalFetched": 26391,
      "pages": 28
    },
    "0406": {
      "eligibleCount": 1922,
      "totalFetched": 32831,
      "pages": 34
    },
    "0405": {
      "eligibleCount": 3335,
      "totalFetched": 45559,
      "pages": 46
    },
    "0431": {
      "eligibleCount": 908,
      "totalFetched": 18287,
      "pages": 21
    },
    "0432": {
      "eligibleCount": 990,
      "totalFetched": 13307,
      "pages": 15
    },
    "0450": {
      "eligibleCount": 1829,
      "totalFetched": 25937,
      "pages": 29
    },
    "0448": {
      "eligibleCount": 3410,
      "totalFetched": 36942,
      "pages": 41
    },
    "0473": {
      "eligibleCount": 779,
      "totalFetched": 16659,
      "pages": 19
    },
    "0451": {
      "eligibleCount": 2553,
      "totalFetched": 27540,
      "pages": 29
    },
    "0482": {
      "eligibleCount": 1819,
      "totalFetched": 26557,
      "pages": 30
    },
    "0498": {
      "eligibleCount": 2762,
      "totalFetched": 32168,
      "pages": 34
    },
    "0489": {
      "eligibleCount": 3145,
      "totalFetched": 41167,
      "pages": 45
    },
    "0512": {
      "eligibleCount": 1834,
      "totalFetched": 25369,
      "pages": 26
    },
    "0523": {
      "eligibleCount": 1272,
      "totalFetched": 13373,
      "pages": 15
    },
    "0532": {
      "eligibleCount": 1267,
      "totalFetched": 15442,
      "pages": 17
    },
    "0534": {
      "eligibleCount": 1228,
      "totalFetched": 18942,
      "pages": 21
    },
    "0513": {
      "eligibleCount": 3900,
      "totalFetched": 45717,
      "pages": 48
    },
    "0547": {
      "eligibleCount": 1518,
      "totalFetched": 25839,
      "pages": 29
    },
    "0553": {
      "eligibleCount": 1743,
      "totalFetched": 23400,
      "pages": 26
    },
    "0531": {
      "eligibleCount": 3305,
      "totalFetched": 43559,
      "pages": 47
    },
    "0542": {
      "eligibleCount": 1931,
      "totalFetched": 40950,
      "pages": 45
    },
    "0556": {
      "eligibleCount": 1392,
      "totalFetched": 27801,
      "pages": 29
    },
    "0589": {
      "eligibleCount": 874,
      "totalFetched": 9162,
      "pages": 10
    },
    "0590": {
      "eligibleCount": 1510,
      "totalFetched": 21343,
      "pages": 24
    },
    "0569": {
      "eligibleCount": 3825,
      "totalFetched": 39371,
      "pages": 44
    },
    "0610": {
      "eligibleCount": 1564,
      "totalFetched": 15044,
      "pages": 16
    },
    "0613": {
      "eligibleCount": 2044,
      "totalFetched": 27677,
      "pages": 33
    },
    "0626": {
      "eligibleCount": 1184,
      "totalFetched": 30778,
      "pages": 35
    },
    "0627": {
      "eligibleCount": 4846,
      "totalFetched": 45494,
      "pages": 50
    },
    "0632": {
      "eligibleCount": 2674,
      "totalFetched": 37834,
      "pages": 41
    },
    "0638": {
      "eligibleCount": 1828,
      "totalFetched": 27646,
      "pages": 31
    },
    "0654": {
      "eligibleCount": 3532,
      "totalFetched": 33704,
      "pages": 38
    },
    "0677": {
      "eligibleCount": 1660,
      "totalFetched": 20771,
      "pages": 25
    },
    "0678": {
      "eligibleCount": 968,
      "totalFetched": 16554,
      "pages": 20
    },
    "0664": {
      "eligibleCount": 2961,
      "totalFetched": 33476,
      "pages": 37
    },
    "0668": {
      "eligibleCount": 3005,
      "totalFetched": 38494,
      "pages": 40
    },
    "0687": {
      "eligibleCount": 3028,
      "totalFetched": 39271,
      "pages": 46
    },
    "0715": {
      "eligibleCount": 3114,
      "totalFetched": 38429,
      "pages": 41
    },
    "0716": {
      "eligibleCount": 3799,
      "totalFetched": 37391,
      "pages": 42
    },
    "0744": {
      "eligibleCount": 761,
      "totalFetched": 6379,
      "pages": 8
    },
    "0703": {
      "eligibleCount": 3488,
      "totalFetched": 43288,
      "pages": 52
    },
    "0743": {
      "eligibleCount": 1995,
      "totalFetched": 20905,
      "pages": 22
    },
    "0755": {
      "eligibleCount": 801,
      "totalFetched": 6430,
      "pages": 7
    },
    "0753": {
      "eligibleCount": 1422,
      "totalFetched": 21241,
      "pages": 22
    },
    "0765": {
      "eligibleCount": 738,
      "totalFetched": 9650,
      "pages": 11
    },
    "0757": {
      "eligibleCount": 1199,
      "totalFetched": 19910,
      "pages": 21
    },
    "0766": {
      "eligibleCount": 1315,
      "totalFetched": 16131,
      "pages": 17
    },
    "0748": {
      "eligibleCount": 3302,
      "totalFetched": 45587,
      "pages": 48
    },
    "0779": {
      "eligibleCount": 1153,
      "totalFetched": 12261,
      "pages": 14
    },
    "0762": {
      "eligibleCount": 3777,
      "totalFetched": 36923,
      "pages": 39
    },
    "0770": {
      "eligibleCount": 2230,
      "totalFetched": 32940,
      "pages": 33
    },
    "0785": {
      "eligibleCount": 1410,
      "totalFetched": 18183,
      "pages": 21
    },
    "0777": {
      "eligibleCount": 2647,
      "totalFetched": 34119,
      "pages": 37
    },
    "0784": {
      "eligibleCount": 2634,
      "totalFetched": 28316,
      "pages": 32
    },
    "0809": {
      "eligibleCount": 1801,
      "totalFetched": 21735,
      "pages": 23
    },
    "0797": {
      "eligibleCount": 2443,
      "totalFetched": 35283,
      "pages": 37
    },
    "0798": {
      "eligibleCount": 2503,
      "totalFetched": 38372,
      "pages": 41
    },
    "0823": {
      "eligibleCount": 2063,
      "totalFetched": 28978,
      "pages": 30
    },
    "0820": {
      "eligibleCount": 2052,
      "totalFetched": 33405,
      "pages": 35
    },
    "0824": {
      "eligibleCount": 2153,
      "totalFetched": 30573,
      "pages": 32
    },
    "0848": {
      "eligibleCount": 881,
      "totalFetched": 11185,
      "pages": 12
    },
    "0847": {
      "eligibleCount": 2056,
      "totalFetched": 22380,
      "pages": 24
    },
    "0840": {
      "eligibleCount": 3009,
      "totalFetched": 28002,
      "pages": 32
    },
    "0851": {
      "eligibleCount": 2074,
      "totalFetched": 18866,
      "pages": 23
    },
    "0858": {
      "eligibleCount": 1420,
      "totalFetched": 20594,
      "pages": 21
    },
    "0866": {
      "eligibleCount": 625,
      "totalFetched": 9880,
      "pages": 11
    },
    "0861": {
      "eligibleCount": 1872,
      "totalFetched": 31270,
      "pages": 32
    },
    "0852": {
      "eligibleCount": 1454,
      "totalFetched": 41944,
      "pages": 45
    },
    "0873": {
      "eligibleCount": 1108,
      "totalFetched": 13336,
      "pages": 14
    },
    "0889": {
      "eligibleCount": 681,
      "totalFetched": 10001,
      "pages": 11
    },
    "0865": {
      "eligibleCount": 3508,
      "totalFetched": 43451,
      "pages": 46
    },
    "0879": {
      "eligibleCount": 2398,
      "totalFetched": 22108,
      "pages": 23
    },
    "0888": {
      "eligibleCount": 1367,
      "totalFetched": 19438,
      "pages": 21
    },
    "0867": {
      "eligibleCount": 3421,
      "totalFetched": 37797,
      "pages": 39
    },
    "0880": {
      "eligibleCount": 1995,
      "totalFetched": 30601,
      "pages": 34
    },
    "0907": {
      "eligibleCount": 1391,
      "totalFetched": 18890,
      "pages": 20
    },
    "0899": {
      "eligibleCount": 1601,
      "totalFetched": 23889,
      "pages": 25
    },
    "0893": {
      "eligibleCount": 2706,
      "totalFetched": 27758,
      "pages": 32
    },
    "0882": {
      "eligibleCount": 2298,
      "totalFetched": 42232,
      "pages": 44
    },
    "0944": {
      "eligibleCount": 1354,
      "totalFetched": 19131,
      "pages": 22
    },
    "0938": {
      "eligibleCount": 1415,
      "totalFetched": 19169,
      "pages": 21
    },
    "0965": {
      "eligibleCount": 1184,
      "totalFetched": 11854,
      "pages": 13
    },
    "0981": {
      "eligibleCount": 406,
      "totalFetched": 8235,
      "pages": 10
    },
    "0971": {
      "eligibleCount": 972,
      "totalFetched": 15640,
      "pages": 17
    },
    "0946": {
      "eligibleCount": 3267,
      "totalFetched": 35035,
      "pages": 37
    },
    "0986": {
      "eligibleCount": 1413,
      "totalFetched": 18933,
      "pages": 22
    },
    "0928": {
      "eligibleCount": 2930,
      "totalFetched": 48956,
      "pages": 50
    },
    "0957": {
      "eligibleCount": 3271,
      "totalFetched": 45535,
      "pages": 48
    },
    "0994": {
      "eligibleCount": 1184,
      "totalFetched": 20001,
      "pages": 22
    },
    "0984": {
      "eligibleCount": 3708,
      "totalFetched": 40253,
      "pages": 42
    },
    "0988": {
      "eligibleCount": 3576,
      "totalFetched": 41447,
      "pages": 43
    }
  }
}
